{
  "version": 2,
  "tree": {
    "name": "root",
    "children": [
      {
        "name": "entry-server.js",
        "children": [
          {
            "name": "C:/Users/Akilesh/Documents/Flyen/src",
            "children": [
              {
                "name": "shared",
                "children": [
                  {
                    "name": "constants/routes.js",
                    "uid": "44362f55-1"
                  },
                  {
                    "name": "services",
                    "children": [
                      {
                        "uid": "44362f55-3",
                        "name": "supabaseClient.js"
                      },
                      {
                        "uid": "44362f55-11",
                        "name": "masterDataService.js"
                      },
                      {
                        "uid": "44362f55-19",
                        "name": "notificationService.js"
                      },
                      {
                        "uid": "44362f55-37",
                        "name": "storageService.js"
                      },
                      {
                        "uid": "44362f55-167",
                        "name": "pageSettingsService.js"
                      }
                    ]
                  },
                  {
                    "name": "utils",
                    "children": [
                      {
                        "uid": "44362f55-5",
                        "name": "mapper.js"
                      },
                      {
                        "uid": "44362f55-7",
                        "name": "logger.js"
                      }
                    ]
                  },
                  {
                    "name": "analytics",
                    "children": [
                      {
                        "uid": "44362f55-23",
                        "name": "analytics.js"
                      },
                      {
                        "uid": "44362f55-25",
                        "name": "AnalyticsProvider.jsx"
                      },
                      {
                        "uid": "44362f55-27",
                        "name": "eventTracker.js"
                      },
                      {
                        "uid": "44362f55-29",
                        "name": "useAnalytics.js"
                      },
                      {
                        "uid": "44362f55-31",
                        "name": "index.js"
                      }
                    ]
                  },
                  {
                    "name": "context/ToastContext.jsx",
                    "uid": "44362f55-45"
                  },
                  {
                    "name": "components",
                    "children": [
                      {
                        "name": "ui",
                        "children": [
                          {
                            "uid": "44362f55-47",
                            "name": "Button.jsx"
                          },
                          {
                            "uid": "44362f55-49",
                            "name": "Modal.jsx"
                          },
                          {
                            "uid": "44362f55-51",
                            "name": "Input.jsx"
                          },
                          {
                            "uid": "44362f55-117",
                            "name": "AdminToolbar.jsx"
                          },
                          {
                            "uid": "44362f55-127",
                            "name": "Badge.jsx"
                          },
                          {
                            "uid": "44362f55-129",
                            "name": "Card.jsx"
                          }
                        ]
                      },
                      {
                        "name": "layout",
                        "children": [
                          {
                            "uid": "44362f55-59",
                            "name": "Footer.jsx"
                          },
                          {
                            "uid": "44362f55-153",
                            "name": "NotificationDropdown.jsx"
                          },
                          {
                            "uid": "44362f55-155",
                            "name": "Header.jsx"
                          },
                          {
                            "uid": "44362f55-157",
                            "name": "GlowBackground.jsx"
                          },
                          {
                            "uid": "44362f55-161",
                            "name": "BottomNavigation.jsx"
                          },
                          {
                            "uid": "44362f55-163",
                            "name": "MobileDrawer.jsx"
                          },
                          {
                            "uid": "44362f55-165",
                            "name": "PageSettingsButton.jsx"
                          },
                          {
                            "uid": "44362f55-169",
                            "name": "PageSettingsDrawer.jsx"
                          },
                          {
                            "uid": "44362f55-175",
                            "name": "MainLayout.jsx"
                          }
                        ]
                      }
                    ]
                  },
                  {
                    "name": "seo",
                    "children": [
                      {
                        "uid": "44362f55-61",
                        "name": "SEO.jsx"
                      },
                      {
                        "name": "config/seoConfig.js",
                        "uid": "44362f55-63"
                      },
                      {
                        "name": "constants/pageTypes.js",
                        "uid": "44362f55-65"
                      },
                      {
                        "name": "builders",
                        "children": [
                          {
                            "uid": "44362f55-67",
                            "name": "canonical.js"
                          },
                          {
                            "uid": "44362f55-91",
                            "name": "metaBuilder.js"
                          },
                          {
                            "uid": "44362f55-93",
                            "name": "ogGenerator.js"
                          },
                          {
                            "uid": "44362f55-95",
                            "name": "twitterCard.js"
                          }
                        ]
                      },
                      {
                        "name": "templates",
                        "children": [
                          {
                            "uid": "44362f55-69",
                            "name": "homeSEO.js"
                          },
                          {
                            "uid": "44362f55-71",
                            "name": "projectListingSEO.js"
                          },
                          {
                            "uid": "44362f55-73",
                            "name": "projectSEO.js"
                          },
                          {
                            "uid": "44362f55-75",
                            "name": "contactSEO.js"
                          },
                          {
                            "uid": "44362f55-77",
                            "name": "printingSEO.js"
                          },
                          {
                            "uid": "44362f55-79",
                            "name": "aboutSEO.js"
                          },
                          {
                            "uid": "44362f55-81",
                            "name": "departmentsSEO.js"
                          },
                          {
                            "uid": "44362f55-83",
                            "name": "privacySEO.js"
                          },
                          {
                            "uid": "44362f55-85",
                            "name": "termsSEO.js"
                          }
                        ]
                      },
                      {
                        "uid": "44362f55-87",
                        "name": "generateSEO.js"
                      },
                      {
                        "uid": "44362f55-89",
                        "name": "routeMetadata.js"
                      },
                      {
                        "name": "schemas",
                        "children": [
                          {
                            "uid": "44362f55-97",
                            "name": "OrganizationSchema.js"
                          },
                          {
                            "uid": "44362f55-99",
                            "name": "WebsiteSchema.js"
                          },
                          {
                            "uid": "44362f55-101",
                            "name": "ProductSchema.js"
                          },
                          {
                            "uid": "44362f55-103",
                            "name": "BreadcrumbSchema.js"
                          },
                          {
                            "uid": "44362f55-105",
                            "name": "LocalBusinessSchema.js"
                          }
                        ]
                      },
                      {
                        "uid": "44362f55-107",
                        "name": "index.js"
                      },
                      {
                        "uid": "44362f55-171",
                        "name": "metadataManager.js"
                      },
                      {
                        "uid": "44362f55-173",
                        "name": "usePageMetadata.js"
                      }
                    ]
                  },
                  {
                    "name": "config",
                    "children": [
                      {
                        "uid": "44362f55-141",
                        "name": "printingProducts.json"
                      },
                      {
                        "uid": "44362f55-159",
                        "name": "navigation.js"
                      }
                    ]
                  }
                ]
              },
              {
                "name": "services/activityLogService.js",
                "uid": "44362f55-9"
              },
              {
                "name": "modules",
                "children": [
                  {
                    "name": "projects",
                    "children": [
                      {
                        "name": "services/projectRepository.js",
                        "uid": "44362f55-13"
                      },
                      {
                        "name": "context/ProjectContext.jsx",
                        "uid": "44362f55-15"
                      },
                      {
                        "name": "hooks",
                        "children": [
                          {
                            "uid": "44362f55-17",
                            "name": "useProjects.js"
                          },
                          {
                            "uid": "44362f55-111",
                            "name": "useFilters.js"
                          },
                          {
                            "uid": "44362f55-113",
                            "name": "useSearch.js"
                          },
                          {
                            "uid": "44362f55-115",
                            "name": "useProjectFilters.js"
                          }
                        ]
                      },
                      {
                        "name": "constants",
                        "children": [
                          {
                            "uid": "44362f55-119",
                            "name": "categories.js"
                          },
                          {
                            "uid": "44362f55-121",
                            "name": "difficulties.js"
                          },
                          {
                            "uid": "44362f55-123",
                            "name": "projectFeatures.js"
                          },
                          {
                            "uid": "44362f55-125",
                            "name": "projectBadges.js"
                          }
                        ]
                      },
                      {
                        "name": "components",
                        "children": [
                          {
                            "uid": "44362f55-131",
                            "name": "ProjectGrid.jsx"
                          },
                          {
                            "uid": "44362f55-135",
                            "name": "RelatedProjects.jsx"
                          }
                        ]
                      },
                      {
                        "name": "pages",
                        "children": [
                          {
                            "uid": "44362f55-133",
                            "name": "ProjectListing.jsx"
                          },
                          {
                            "uid": "44362f55-139",
                            "name": "ProjectDetails.jsx"
                          }
                        ]
                      }
                    ]
                  },
                  {
                    "name": "enquiries",
                    "children": [
                      {
                        "name": "services/enquiryService.js",
                        "uid": "44362f55-21"
                      },
                      {
                        "name": "context/EnquiryContext.jsx",
                        "uid": "44362f55-33"
                      },
                      {
                        "name": "hooks/useEnquiries.js",
                        "uid": "44362f55-35"
                      }
                    ]
                  },
                  {
                    "name": "auth",
                    "children": [
                      {
                        "name": "services",
                        "children": [
                          {
                            "uid": "44362f55-39",
                            "name": "userService.js"
                          },
                          {
                            "uid": "44362f55-41",
                            "name": "authService.js"
                          }
                        ]
                      },
                      {
                        "name": "context/AuthContext.jsx",
                        "uid": "44362f55-43"
                      },
                      {
                        "name": "components/ProgressiveAuthModal.jsx",
                        "uid": "44362f55-137"
                      }
                    ]
                  },
                  {
                    "name": "settings",
                    "children": [
                      {
                        "name": "services/settingsService.js",
                        "uid": "44362f55-53"
                      },
                      {
                        "name": "context/SettingsContext.jsx",
                        "uid": "44362f55-55"
                      },
                      {
                        "name": "hooks/useSettings.js",
                        "uid": "44362f55-57"
                      }
                    ]
                  },
                  {
                    "name": "public",
                    "children": [
                      {
                        "name": "pages",
                        "children": [
                          {
                            "uid": "44362f55-109",
                            "name": "Home.jsx"
                          },
                          {
                            "uid": "44362f55-145",
                            "name": "PrintingCatalog.jsx"
                          },
                          {
                            "uid": "44362f55-151",
                            "name": "Contact.jsx"
                          }
                        ]
                      },
                      {
                        "name": "hooks/usePrintingProducts.js",
                        "uid": "44362f55-143"
                      }
                    ]
                  },
                  {
                    "name": "contact/services",
                    "children": [
                      {
                        "uid": "44362f55-147",
                        "name": "contactService.js"
                      },
                      {
                        "uid": "44362f55-149",
                        "name": "emailService.js"
                      }
                    ]
                  }
                ]
              },
              {
                "uid": "44362f55-177",
                "name": "entry-server.jsx"
              }
            ]
          }
        ]
      }
    ],
    "isRoot": true
  },
  "nodeParts": {
    "44362f55-1": {
      "renderedLength": 1150,
      "gzipLength": 0,
      "brotliLength": 0,
      "metaUid": "44362f55-0"
    },
    "44362f55-3": {
      "renderedLength": 416,
      "gzipLength": 0,
      "brotliLength": 0,
      "metaUid": "44362f55-2"
    },
    "44362f55-5": {
      "renderedLength": 5384,
      "gzipLength": 0,
      "brotliLength": 0,
      "metaUid": "44362f55-4"
    },
    "44362f55-7": {
      "renderedLength": 152,
      "gzipLength": 0,
      "brotliLength": 0,
      "metaUid": "44362f55-6"
    },
    "44362f55-9": {
      "renderedLength": 10354,
      "gzipLength": 0,
      "brotliLength": 0,
      "metaUid": "44362f55-8"
    },
    "44362f55-11": {
      "renderedLength": 4458,
      "gzipLength": 0,
      "brotliLength": 0,
      "metaUid": "44362f55-10"
    },
    "44362f55-13": {
      "renderedLength": 7851,
      "gzipLength": 0,
      "brotliLength": 0,
      "metaUid": "44362f55-12"
    },
    "44362f55-15": {
      "renderedLength": 1989,
      "gzipLength": 0,
      "brotliLength": 0,
      "metaUid": "44362f55-14"
    },
    "44362f55-17": {
      "renderedLength": 1358,
      "gzipLength": 0,
      "brotliLength": 0,
      "metaUid": "44362f55-16"
    },
    "44362f55-19": {
      "renderedLength": 6278,
      "gzipLength": 0,
      "brotliLength": 0,
      "metaUid": "44362f55-18"
    },
    "44362f55-21": {
      "renderedLength": 5981,
      "gzipLength": 0,
      "brotliLength": 0,
      "metaUid": "44362f55-20"
    },
    "44362f55-23": {
      "renderedLength": 455,
      "gzipLength": 0,
      "brotliLength": 0,
      "metaUid": "44362f55-22"
    },
    "44362f55-25": {
      "renderedLength": 106,
      "gzipLength": 0,
      "brotliLength": 0,
      "metaUid": "44362f55-24"
    },
    "44362f55-27": {
      "renderedLength": 2233,
      "gzipLength": 0,
      "brotliLength": 0,
      "metaUid": "44362f55-26"
    },
    "44362f55-29": {
      "renderedLength": 0,
      "gzipLength": 0,
      "brotliLength": 0,
      "metaUid": "44362f55-28"
    },
    "44362f55-31": {
      "renderedLength": 0,
      "gzipLength": 0,
      "brotliLength": 0,
      "metaUid": "44362f55-30"
    },
    "44362f55-33": {
      "renderedLength": 2144,
      "gzipLength": 0,
      "brotliLength": 0,
      "metaUid": "44362f55-32"
    },
    "44362f55-35": {
      "renderedLength": 393,
      "gzipLength": 0,
      "brotliLength": 0,
      "metaUid": "44362f55-34"
    },
    "44362f55-37": {
      "renderedLength": 6411,
      "gzipLength": 0,
      "brotliLength": 0,
      "metaUid": "44362f55-36"
    },
    "44362f55-39": {
      "renderedLength": 6530,
      "gzipLength": 0,
      "brotliLength": 0,
      "metaUid": "44362f55-38"
    },
    "44362f55-41": {
      "renderedLength": 6425,
      "gzipLength": 0,
      "brotliLength": 0,
      "metaUid": "44362f55-40"
    },
    "44362f55-43": {
      "renderedLength": 4139,
      "gzipLength": 0,
      "brotliLength": 0,
      "metaUid": "44362f55-42"
    },
    "44362f55-45": {
      "renderedLength": 3727,
      "gzipLength": 0,
      "brotliLength": 0,
      "metaUid": "44362f55-44"
    },
    "44362f55-47": {
      "renderedLength": 375,
      "gzipLength": 0,
      "brotliLength": 0,
      "metaUid": "44362f55-46"
    },
    "44362f55-49": {
      "renderedLength": 413,
      "gzipLength": 0,
      "brotliLength": 0,
      "metaUid": "44362f55-48"
    },
    "44362f55-51": {
      "renderedLength": 351,
      "gzipLength": 0,
      "brotliLength": 0,
      "metaUid": "44362f55-50"
    },
    "44362f55-53": {
      "renderedLength": 2109,
      "gzipLength": 0,
      "brotliLength": 0,
      "metaUid": "44362f55-52"
    },
    "44362f55-55": {
      "renderedLength": 7628,
      "gzipLength": 0,
      "brotliLength": 0,
      "metaUid": "44362f55-54"
    },
    "44362f55-57": {
      "renderedLength": 283,
      "gzipLength": 0,
      "brotliLength": 0,
      "metaUid": "44362f55-56"
    },
    "44362f55-59": {
      "renderedLength": 11391,
      "gzipLength": 0,
      "brotliLength": 0,
      "metaUid": "44362f55-58"
    },
    "44362f55-61": {
      "renderedLength": 237,
      "gzipLength": 0,
      "brotliLength": 0,
      "metaUid": "44362f55-60"
    },
    "44362f55-63": {
      "renderedLength": 552,
      "gzipLength": 0,
      "brotliLength": 0,
      "metaUid": "44362f55-62"
    },
    "44362f55-65": {
      "renderedLength": 298,
      "gzipLength": 0,
      "brotliLength": 0,
      "metaUid": "44362f55-64"
    },
    "44362f55-67": {
      "renderedLength": 307,
      "gzipLength": 0,
      "brotliLength": 0,
      "metaUid": "44362f55-66"
    },
    "44362f55-69": {
      "renderedLength": 326,
      "gzipLength": 0,
      "brotliLength": 0,
      "metaUid": "44362f55-68"
    },
    "44362f55-71": {
      "renderedLength": 365,
      "gzipLength": 0,
      "brotliLength": 0,
      "metaUid": "44362f55-70"
    },
    "44362f55-73": {
      "renderedLength": 703,
      "gzipLength": 0,
      "brotliLength": 0,
      "metaUid": "44362f55-72"
    },
    "44362f55-75": {
      "renderedLength": 331,
      "gzipLength": 0,
      "brotliLength": 0,
      "metaUid": "44362f55-74"
    },
    "44362f55-77": {
      "renderedLength": 313,
      "gzipLength": 0,
      "brotliLength": 0,
      "metaUid": "44362f55-76"
    },
    "44362f55-79": {
      "renderedLength": 298,
      "gzipLength": 0,
      "brotliLength": 0,
      "metaUid": "44362f55-78"
    },
    "44362f55-81": {
      "renderedLength": 347,
      "gzipLength": 0,
      "brotliLength": 0,
      "metaUid": "44362f55-80"
    },
    "44362f55-83": {
      "renderedLength": 347,
      "gzipLength": 0,
      "brotliLength": 0,
      "metaUid": "44362f55-82"
    },
    "44362f55-85": {
      "renderedLength": 352,
      "gzipLength": 0,
      "brotliLength": 0,
      "metaUid": "44362f55-84"
    },
    "44362f55-87": {
      "renderedLength": 603,
      "gzipLength": 0,
      "brotliLength": 0,
      "metaUid": "44362f55-86"
    },
    "44362f55-89": {
      "renderedLength": 1681,
      "gzipLength": 0,
      "brotliLength": 0,
      "metaUid": "44362f55-88"
    },
    "44362f55-91": {
      "renderedLength": 1564,
      "gzipLength": 0,
      "brotliLength": 0,
      "metaUid": "44362f55-90"
    },
    "44362f55-93": {
      "renderedLength": 327,
      "gzipLength": 0,
      "brotliLength": 0,
      "metaUid": "44362f55-92"
    },
    "44362f55-95": {
      "renderedLength": 430,
      "gzipLength": 0,
      "brotliLength": 0,
      "metaUid": "44362f55-94"
    },
    "44362f55-97": {
      "renderedLength": 670,
      "gzipLength": 0,
      "brotliLength": 0,
      "metaUid": "44362f55-96"
    },
    "44362f55-99": {
      "renderedLength": 411,
      "gzipLength": 0,
      "brotliLength": 0,
      "metaUid": "44362f55-98"
    },
    "44362f55-101": {
      "renderedLength": 820,
      "gzipLength": 0,
      "brotliLength": 0,
      "metaUid": "44362f55-100"
    },
    "44362f55-103": {
      "renderedLength": 485,
      "gzipLength": 0,
      "brotliLength": 0,
      "metaUid": "44362f55-102"
    },
    "44362f55-105": {
      "renderedLength": 572,
      "gzipLength": 0,
      "brotliLength": 0,
      "metaUid": "44362f55-104"
    },
    "44362f55-107": {
      "renderedLength": 0,
      "gzipLength": 0,
      "brotliLength": 0,
      "metaUid": "44362f55-106"
    },
    "44362f55-109": {
      "renderedLength": 47184,
      "gzipLength": 0,
      "brotliLength": 0,
      "metaUid": "44362f55-108"
    },
    "44362f55-111": {
      "renderedLength": 1559,
      "gzipLength": 0,
      "brotliLength": 0,
      "metaUid": "44362f55-110"
    },
    "44362f55-113": {
      "renderedLength": 2033,
      "gzipLength": 0,
      "brotliLength": 0,
      "metaUid": "44362f55-112"
    },
    "44362f55-115": {
      "renderedLength": 2689,
      "gzipLength": 0,
      "brotliLength": 0,
      "metaUid": "44362f55-114"
    },
    "44362f55-117": {
      "renderedLength": 7086,
      "gzipLength": 0,
      "brotliLength": 0,
      "metaUid": "44362f55-116"
    },
    "44362f55-119": {
      "renderedLength": 555,
      "gzipLength": 0,
      "brotliLength": 0,
      "metaUid": "44362f55-118"
    },
    "44362f55-121": {
      "renderedLength": 455,
      "gzipLength": 0,
      "brotliLength": 0,
      "metaUid": "44362f55-120"
    },
    "44362f55-123": {
      "renderedLength": 547,
      "gzipLength": 0,
      "brotliLength": 0,
      "metaUid": "44362f55-122"
    },
    "44362f55-125": {
      "renderedLength": 406,
      "gzipLength": 0,
      "brotliLength": 0,
      "metaUid": "44362f55-124"
    },
    "44362f55-127": {
      "renderedLength": 414,
      "gzipLength": 0,
      "brotliLength": 0,
      "metaUid": "44362f55-126"
    },
    "44362f55-129": {
      "renderedLength": 246,
      "gzipLength": 0,
      "brotliLength": 0,
      "metaUid": "44362f55-128"
    },
    "44362f55-131": {
      "renderedLength": 5178,
      "gzipLength": 0,
      "brotliLength": 0,
      "metaUid": "44362f55-130"
    },
    "44362f55-133": {
      "renderedLength": 31469,
      "gzipLength": 0,
      "brotliLength": 0,
      "metaUid": "44362f55-132"
    },
    "44362f55-135": {
      "renderedLength": 0,
      "gzipLength": 0,
      "brotliLength": 0,
      "metaUid": "44362f55-134"
    },
    "44362f55-137": {
      "renderedLength": 3082,
      "gzipLength": 0,
      "brotliLength": 0,
      "metaUid": "44362f55-136"
    },
    "44362f55-139": {
      "renderedLength": 59929,
      "gzipLength": 0,
      "brotliLength": 0,
      "metaUid": "44362f55-138"
    },
    "44362f55-141": {
      "renderedLength": 1077,
      "gzipLength": 0,
      "brotliLength": 0,
      "metaUid": "44362f55-140"
    },
    "44362f55-143": {
      "renderedLength": 460,
      "gzipLength": 0,
      "brotliLength": 0,
      "metaUid": "44362f55-142"
    },
    "44362f55-145": {
      "renderedLength": 17793,
      "gzipLength": 0,
      "brotliLength": 0,
      "metaUid": "44362f55-144"
    },
    "44362f55-147": {
      "renderedLength": 1400,
      "gzipLength": 0,
      "brotliLength": 0,
      "metaUid": "44362f55-146"
    },
    "44362f55-149": {
      "renderedLength": 2729,
      "gzipLength": 0,
      "brotliLength": 0,
      "metaUid": "44362f55-148"
    },
    "44362f55-151": {
      "renderedLength": 27110,
      "gzipLength": 0,
      "brotliLength": 0,
      "metaUid": "44362f55-150"
    },
    "44362f55-153": {
      "renderedLength": 7309,
      "gzipLength": 0,
      "brotliLength": 0,
      "metaUid": "44362f55-152"
    },
    "44362f55-155": {
      "renderedLength": 23650,
      "gzipLength": 0,
      "brotliLength": 0,
      "metaUid": "44362f55-154"
    },
    "44362f55-157": {
      "renderedLength": 172,
      "gzipLength": 0,
      "brotliLength": 0,
      "metaUid": "44362f55-156"
    },
    "44362f55-159": {
      "renderedLength": 1540,
      "gzipLength": 0,
      "brotliLength": 0,
      "metaUid": "44362f55-158"
    },
    "44362f55-161": {
      "renderedLength": 7494,
      "gzipLength": 0,
      "brotliLength": 0,
      "metaUid": "44362f55-160"
    },
    "44362f55-163": {
      "renderedLength": 15564,
      "gzipLength": 0,
      "brotliLength": 0,
      "metaUid": "44362f55-162"
    },
    "44362f55-165": {
      "renderedLength": 2456,
      "gzipLength": 0,
      "brotliLength": 0,
      "metaUid": "44362f55-164"
    },
    "44362f55-167": {
      "renderedLength": 4271,
      "gzipLength": 0,
      "brotliLength": 0,
      "metaUid": "44362f55-166"
    },
    "44362f55-169": {
      "renderedLength": 25570,
      "gzipLength": 0,
      "brotliLength": 0,
      "metaUid": "44362f55-168"
    },
    "44362f55-171": {
      "renderedLength": 3946,
      "gzipLength": 0,
      "brotliLength": 0,
      "metaUid": "44362f55-170"
    },
    "44362f55-173": {
      "renderedLength": 2572,
      "gzipLength": 0,
      "brotliLength": 0,
      "metaUid": "44362f55-172"
    },
    "44362f55-175": {
      "renderedLength": 1754,
      "gzipLength": 0,
      "brotliLength": 0,
      "metaUid": "44362f55-174"
    },
    "44362f55-177": {
      "renderedLength": 1361,
      "gzipLength": 0,
      "brotliLength": 0,
      "metaUid": "44362f55-176"
    }
  },
  "nodeMetas": {
    "44362f55-0": {
      "id": "C:/Users/Akilesh/Documents/Flyen/src/shared/constants/routes.js",
      "moduleParts": {
        "entry-server.js": "44362f55-1"
      },
      "imported": [],
      "importedBy": [
        {
          "uid": "44362f55-176"
        },
        {
          "uid": "44362f55-108"
        },
        {
          "uid": "44362f55-132"
        },
        {
          "uid": "44362f55-138"
        },
        {
          "uid": "44362f55-144"
        },
        {
          "uid": "44362f55-150"
        },
        {
          "uid": "44362f55-130"
        },
        {
          "uid": "44362f55-136"
        },
        {
          "uid": "44362f55-154"
        },
        {
          "uid": "44362f55-160"
        },
        {
          "uid": "44362f55-162"
        },
        {
          "uid": "44362f55-172"
        },
        {
          "uid": "44362f55-88"
        }
      ]
    },
    "44362f55-2": {
      "id": "C:/Users/Akilesh/Documents/Flyen/src/shared/services/supabaseClient.js",
      "moduleParts": {
        "entry-server.js": "44362f55-3"
      },
      "imported": [
        {
          "uid": "44362f55-190"
        }
      ],
      "importedBy": [
        {
          "uid": "44362f55-10"
        },
        {
          "uid": "44362f55-146"
        },
        {
          "uid": "44362f55-52"
        },
        {
          "uid": "44362f55-12"
        },
        {
          "uid": "44362f55-40"
        },
        {
          "uid": "44362f55-38"
        },
        {
          "uid": "44362f55-20"
        },
        {
          "uid": "44362f55-154"
        },
        {
          "uid": "44362f55-172"
        },
        {
          "uid": "44362f55-18"
        },
        {
          "uid": "44362f55-8"
        },
        {
          "uid": "44362f55-36"
        },
        {
          "uid": "44362f55-166"
        }
      ]
    },
    "44362f55-4": {
      "id": "C:/Users/Akilesh/Documents/Flyen/src/shared/utils/mapper.js",
      "moduleParts": {
        "entry-server.js": "44362f55-5"
      },
      "imported": [],
      "importedBy": [
        {
          "uid": "44362f55-146"
        },
        {
          "uid": "44362f55-12"
        },
        {
          "uid": "44362f55-20"
        }
      ]
    },
    "44362f55-6": {
      "id": "C:/Users/Akilesh/Documents/Flyen/src/shared/utils/logger.js",
      "moduleParts": {
        "entry-server.js": "44362f55-7"
      },
      "imported": [],
      "importedBy": [
        {
          "uid": "44362f55-54"
        },
        {
          "uid": "44362f55-42"
        },
        {
          "uid": "44362f55-52"
        },
        {
          "uid": "44362f55-40"
        },
        {
          "uid": "44362f55-38"
        },
        {
          "uid": "44362f55-8"
        },
        {
          "uid": "44362f55-36"
        }
      ]
    },
    "44362f55-8": {
      "id": "C:/Users/Akilesh/Documents/Flyen/src/services/activityLogService.js",
      "moduleParts": {
        "entry-server.js": "44362f55-9"
      },
      "imported": [
        {
          "uid": "44362f55-2"
        },
        {
          "uid": "44362f55-6"
        }
      ],
      "importedBy": [
        {
          "uid": "44362f55-52"
        },
        {
          "uid": "44362f55-12"
        },
        {
          "uid": "44362f55-40"
        },
        {
          "uid": "44362f55-20"
        },
        {
          "uid": "44362f55-18"
        },
        {
          "uid": "44362f55-166"
        }
      ]
    },
    "44362f55-10": {
      "id": "C:/Users/Akilesh/Documents/Flyen/src/shared/services/masterDataService.js",
      "moduleParts": {
        "entry-server.js": "44362f55-11"
      },
      "imported": [
        {
          "uid": "44362f55-2"
        }
      ],
      "importedBy": [
        {
          "uid": "44362f55-132"
        },
        {
          "uid": "44362f55-12"
        }
      ]
    },
    "44362f55-12": {
      "id": "C:/Users/Akilesh/Documents/Flyen/src/modules/projects/services/projectRepository.js",
      "moduleParts": {
        "entry-server.js": "44362f55-13"
      },
      "imported": [
        {
          "uid": "44362f55-2"
        },
        {
          "uid": "44362f55-4"
        },
        {
          "uid": "44362f55-8"
        },
        {
          "uid": "44362f55-10"
        }
      ],
      "importedBy": [
        {
          "uid": "44362f55-14"
        }
      ]
    },
    "44362f55-14": {
      "id": "C:/Users/Akilesh/Documents/Flyen/src/modules/projects/context/ProjectContext.jsx",
      "moduleParts": {
        "entry-server.js": "44362f55-15"
      },
      "imported": [
        {
          "uid": "44362f55-178"
        },
        {
          "uid": "44362f55-12"
        },
        {
          "uid": "44362f55-182"
        }
      ],
      "importedBy": [
        {
          "uid": "44362f55-176"
        },
        {
          "uid": "44362f55-16"
        }
      ]
    },
    "44362f55-16": {
      "id": "C:/Users/Akilesh/Documents/Flyen/src/modules/projects/hooks/useProjects.js",
      "moduleParts": {
        "entry-server.js": "44362f55-17"
      },
      "imported": [
        {
          "uid": "44362f55-178"
        },
        {
          "uid": "44362f55-14"
        }
      ],
      "importedBy": [
        {
          "uid": "44362f55-108"
        },
        {
          "uid": "44362f55-132"
        },
        {
          "uid": "44362f55-138"
        }
      ]
    },
    "44362f55-18": {
      "id": "C:/Users/Akilesh/Documents/Flyen/src/shared/services/notificationService.js",
      "moduleParts": {
        "entry-server.js": "44362f55-19"
      },
      "imported": [
        {
          "uid": "44362f55-2"
        },
        {
          "uid": "44362f55-8"
        }
      ],
      "importedBy": [
        {
          "uid": "44362f55-148"
        },
        {
          "uid": "44362f55-40"
        },
        {
          "uid": "44362f55-20"
        },
        {
          "uid": "44362f55-154"
        },
        {
          "uid": "44362f55-152"
        }
      ]
    },
    "44362f55-20": {
      "id": "C:/Users/Akilesh/Documents/Flyen/src/modules/enquiries/services/enquiryService.js",
      "moduleParts": {
        "entry-server.js": "44362f55-21"
      },
      "imported": [
        {
          "uid": "44362f55-2"
        },
        {
          "uid": "44362f55-4"
        },
        {
          "uid": "44362f55-8"
        },
        {
          "uid": "44362f55-18"
        }
      ],
      "importedBy": [
        {
          "uid": "44362f55-42"
        },
        {
          "uid": "44362f55-32"
        }
      ]
    },
    "44362f55-22": {
      "id": "C:/Users/Akilesh/Documents/Flyen/src/shared/analytics/analytics.js",
      "moduleParts": {
        "entry-server.js": "44362f55-23"
      },
      "imported": [
        {
          "uid": "44362f55-188"
        }
      ],
      "importedBy": [
        {
          "uid": "44362f55-30"
        },
        {
          "uid": "44362f55-24"
        },
        {
          "uid": "44362f55-28"
        },
        {
          "uid": "44362f55-26"
        }
      ]
    },
    "44362f55-24": {
      "id": "C:/Users/Akilesh/Documents/Flyen/src/shared/analytics/AnalyticsProvider.jsx",
      "moduleParts": {
        "entry-server.js": "44362f55-25"
      },
      "imported": [
        {
          "uid": "44362f55-178"
        },
        {
          "uid": "44362f55-181"
        },
        {
          "uid": "44362f55-22"
        },
        {
          "uid": "44362f55-182"
        }
      ],
      "importedBy": [
        {
          "uid": "44362f55-30"
        },
        {
          "uid": "44362f55-28"
        }
      ]
    },
    "44362f55-26": {
      "id": "C:/Users/Akilesh/Documents/Flyen/src/shared/analytics/eventTracker.js",
      "moduleParts": {
        "entry-server.js": "44362f55-27"
      },
      "imported": [
        {
          "uid": "44362f55-22"
        }
      ],
      "importedBy": [
        {
          "uid": "44362f55-30"
        },
        {
          "uid": "44362f55-28"
        }
      ]
    },
    "44362f55-28": {
      "id": "C:/Users/Akilesh/Documents/Flyen/src/shared/analytics/useAnalytics.js",
      "moduleParts": {
        "entry-server.js": "44362f55-29"
      },
      "imported": [
        {
          "uid": "44362f55-178"
        },
        {
          "uid": "44362f55-24"
        },
        {
          "uid": "44362f55-26"
        },
        {
          "uid": "44362f55-22"
        }
      ],
      "importedBy": [
        {
          "uid": "44362f55-30"
        }
      ]
    },
    "44362f55-30": {
      "id": "C:/Users/Akilesh/Documents/Flyen/src/shared/analytics/index.js",
      "moduleParts": {
        "entry-server.js": "44362f55-31"
      },
      "imported": [
        {
          "uid": "44362f55-24"
        },
        {
          "uid": "44362f55-28"
        },
        {
          "uid": "44362f55-22"
        },
        {
          "uid": "44362f55-26"
        },
        {
          "uid": "44362f55-188"
        }
      ],
      "importedBy": [
        {
          "uid": "44362f55-132"
        },
        {
          "uid": "44362f55-138"
        },
        {
          "uid": "44362f55-32"
        }
      ]
    },
    "44362f55-32": {
      "id": "C:/Users/Akilesh/Documents/Flyen/src/modules/enquiries/context/EnquiryContext.jsx",
      "moduleParts": {
        "entry-server.js": "44362f55-33"
      },
      "imported": [
        {
          "uid": "44362f55-178"
        },
        {
          "uid": "44362f55-20"
        },
        {
          "uid": "44362f55-30"
        },
        {
          "uid": "44362f55-182"
        }
      ],
      "importedBy": [
        {
          "uid": "44362f55-176"
        },
        {
          "uid": "44362f55-34"
        }
      ]
    },
    "44362f55-34": {
      "id": "C:/Users/Akilesh/Documents/Flyen/src/modules/enquiries/hooks/useEnquiries.js",
      "moduleParts": {
        "entry-server.js": "44362f55-35"
      },
      "imported": [
        {
          "uid": "44362f55-178"
        },
        {
          "uid": "44362f55-32"
        }
      ],
      "importedBy": [
        {
          "uid": "44362f55-108"
        },
        {
          "uid": "44362f55-132"
        },
        {
          "uid": "44362f55-138"
        }
      ]
    },
    "44362f55-36": {
      "id": "C:/Users/Akilesh/Documents/Flyen/src/shared/services/storageService.js",
      "moduleParts": {
        "entry-server.js": "44362f55-37"
      },
      "imported": [
        {
          "uid": "44362f55-2"
        },
        {
          "uid": "44362f55-6"
        }
      ],
      "importedBy": [
        {
          "uid": "44362f55-38"
        }
      ]
    },
    "44362f55-38": {
      "id": "C:/Users/Akilesh/Documents/Flyen/src/modules/auth/services/userService.js",
      "moduleParts": {
        "entry-server.js": "44362f55-39"
      },
      "imported": [
        {
          "uid": "44362f55-2"
        },
        {
          "uid": "44362f55-36"
        },
        {
          "uid": "44362f55-6"
        }
      ],
      "importedBy": [
        {
          "uid": "44362f55-42"
        },
        {
          "uid": "44362f55-40"
        }
      ]
    },
    "44362f55-40": {
      "id": "C:/Users/Akilesh/Documents/Flyen/src/modules/auth/services/authService.js",
      "moduleParts": {
        "entry-server.js": "44362f55-41"
      },
      "imported": [
        {
          "uid": "44362f55-2"
        },
        {
          "uid": "44362f55-38"
        },
        {
          "uid": "44362f55-6"
        },
        {
          "uid": "44362f55-8"
        },
        {
          "uid": "44362f55-18"
        }
      ],
      "importedBy": [
        {
          "uid": "44362f55-42"
        }
      ]
    },
    "44362f55-42": {
      "id": "C:/Users/Akilesh/Documents/Flyen/src/modules/auth/context/AuthContext.jsx",
      "moduleParts": {
        "entry-server.js": "44362f55-43"
      },
      "imported": [
        {
          "uid": "44362f55-178"
        },
        {
          "uid": "44362f55-40"
        },
        {
          "uid": "44362f55-38"
        },
        {
          "uid": "44362f55-20"
        },
        {
          "uid": "44362f55-6"
        },
        {
          "uid": "44362f55-182"
        }
      ],
      "importedBy": [
        {
          "uid": "44362f55-176"
        },
        {
          "uid": "44362f55-108"
        },
        {
          "uid": "44362f55-132"
        },
        {
          "uid": "44362f55-138"
        },
        {
          "uid": "44362f55-144"
        },
        {
          "uid": "44362f55-154"
        },
        {
          "uid": "44362f55-160"
        },
        {
          "uid": "44362f55-162"
        },
        {
          "uid": "44362f55-164"
        }
      ]
    },
    "44362f55-44": {
      "id": "C:/Users/Akilesh/Documents/Flyen/src/shared/context/ToastContext.jsx",
      "moduleParts": {
        "entry-server.js": "44362f55-45"
      },
      "imported": [
        {
          "uid": "44362f55-178"
        },
        {
          "uid": "44362f55-182"
        }
      ],
      "importedBy": [
        {
          "uid": "44362f55-176"
        },
        {
          "uid": "44362f55-108"
        },
        {
          "uid": "44362f55-132"
        },
        {
          "uid": "44362f55-138"
        },
        {
          "uid": "44362f55-144"
        },
        {
          "uid": "44362f55-168"
        }
      ]
    },
    "44362f55-46": {
      "id": "C:/Users/Akilesh/Documents/Flyen/src/shared/components/ui/Button.jsx",
      "moduleParts": {
        "entry-server.js": "44362f55-47"
      },
      "imported": [
        {
          "uid": "44362f55-178"
        },
        {
          "uid": "44362f55-182"
        }
      ],
      "importedBy": [
        {
          "uid": "44362f55-108"
        },
        {
          "uid": "44362f55-132"
        },
        {
          "uid": "44362f55-138"
        },
        {
          "uid": "44362f55-144"
        },
        {
          "uid": "44362f55-150"
        },
        {
          "uid": "44362f55-116"
        },
        {
          "uid": "44362f55-130"
        },
        {
          "uid": "44362f55-136"
        },
        {
          "uid": "44362f55-154"
        },
        {
          "uid": "44362f55-162"
        }
      ]
    },
    "44362f55-48": {
      "id": "C:/Users/Akilesh/Documents/Flyen/src/shared/components/ui/Modal.jsx",
      "moduleParts": {
        "entry-server.js": "44362f55-49"
      },
      "imported": [
        {
          "uid": "44362f55-178"
        },
        {
          "uid": "44362f55-182"
        }
      ],
      "importedBy": [
        {
          "uid": "44362f55-108"
        },
        {
          "uid": "44362f55-132"
        },
        {
          "uid": "44362f55-138"
        },
        {
          "uid": "44362f55-144"
        },
        {
          "uid": "44362f55-150"
        },
        {
          "uid": "44362f55-136"
        },
        {
          "uid": "44362f55-154"
        }
      ]
    },
    "44362f55-50": {
      "id": "C:/Users/Akilesh/Documents/Flyen/src/shared/components/ui/Input.jsx",
      "moduleParts": {
        "entry-server.js": "44362f55-51"
      },
      "imported": [
        {
          "uid": "44362f55-178"
        },
        {
          "uid": "44362f55-182"
        }
      ],
      "importedBy": [
        {
          "uid": "44362f55-108"
        },
        {
          "uid": "44362f55-132"
        },
        {
          "uid": "44362f55-138"
        },
        {
          "uid": "44362f55-144"
        },
        {
          "uid": "44362f55-150"
        },
        {
          "uid": "44362f55-116"
        }
      ]
    },
    "44362f55-52": {
      "id": "C:/Users/Akilesh/Documents/Flyen/src/modules/settings/services/settingsService.js",
      "moduleParts": {
        "entry-server.js": "44362f55-53"
      },
      "imported": [
        {
          "uid": "44362f55-2"
        },
        {
          "uid": "44362f55-6"
        },
        {
          "uid": "44362f55-8"
        }
      ],
      "importedBy": [
        {
          "uid": "44362f55-54"
        }
      ]
    },
    "44362f55-54": {
      "id": "C:/Users/Akilesh/Documents/Flyen/src/modules/settings/context/SettingsContext.jsx",
      "moduleParts": {
        "entry-server.js": "44362f55-55"
      },
      "imported": [
        {
          "uid": "44362f55-178"
        },
        {
          "uid": "44362f55-52"
        },
        {
          "uid": "44362f55-6"
        },
        {
          "uid": "44362f55-182"
        }
      ],
      "importedBy": [
        {
          "uid": "44362f55-176"
        },
        {
          "uid": "44362f55-56"
        }
      ]
    },
    "44362f55-56": {
      "id": "C:/Users/Akilesh/Documents/Flyen/src/modules/settings/hooks/useSettings.js",
      "moduleParts": {
        "entry-server.js": "44362f55-57"
      },
      "imported": [
        {
          "uid": "44362f55-178"
        },
        {
          "uid": "44362f55-54"
        }
      ],
      "importedBy": [
        {
          "uid": "44362f55-108"
        },
        {
          "uid": "44362f55-138"
        },
        {
          "uid": "44362f55-150"
        },
        {
          "uid": "44362f55-58"
        },
        {
          "uid": "44362f55-154"
        }
      ]
    },
    "44362f55-58": {
      "id": "C:/Users/Akilesh/Documents/Flyen/src/shared/components/layout/Footer.jsx",
      "moduleParts": {
        "entry-server.js": "44362f55-59"
      },
      "imported": [
        {
          "uid": "44362f55-178"
        },
        {
          "uid": "44362f55-181"
        },
        {
          "uid": "44362f55-56"
        },
        {
          "uid": "44362f55-182"
        }
      ],
      "importedBy": [
        {
          "uid": "44362f55-108"
        }
      ]
    },
    "44362f55-60": {
      "id": "C:/Users/Akilesh/Documents/Flyen/src/shared/seo/SEO.jsx",
      "moduleParts": {
        "entry-server.js": "44362f55-61"
      },
      "imported": [
        {
          "uid": "44362f55-178"
        }
      ],
      "importedBy": [
        {
          "uid": "44362f55-106"
        }
      ]
    },
    "44362f55-62": {
      "id": "C:/Users/Akilesh/Documents/Flyen/src/shared/seo/config/seoConfig.js",
      "moduleParts": {
        "entry-server.js": "44362f55-63"
      },
      "imported": [],
      "importedBy": [
        {
          "uid": "44362f55-106"
        },
        {
          "uid": "44362f55-170"
        },
        {
          "uid": "44362f55-68"
        },
        {
          "uid": "44362f55-70"
        },
        {
          "uid": "44362f55-72"
        },
        {
          "uid": "44362f55-74"
        },
        {
          "uid": "44362f55-76"
        },
        {
          "uid": "44362f55-78"
        },
        {
          "uid": "44362f55-80"
        },
        {
          "uid": "44362f55-82"
        },
        {
          "uid": "44362f55-84"
        }
      ]
    },
    "44362f55-64": {
      "id": "C:/Users/Akilesh/Documents/Flyen/src/shared/seo/constants/pageTypes.js",
      "moduleParts": {
        "entry-server.js": "44362f55-65"
      },
      "imported": [],
      "importedBy": [
        {
          "uid": "44362f55-106"
        },
        {
          "uid": "44362f55-172"
        },
        {
          "uid": "44362f55-86"
        },
        {
          "uid": "44362f55-88"
        },
        {
          "uid": "44362f55-170"
        }
      ]
    },
    "44362f55-66": {
      "id": "C:/Users/Akilesh/Documents/Flyen/src/shared/seo/builders/canonical.js",
      "moduleParts": {
        "entry-server.js": "44362f55-67"
      },
      "imported": [],
      "importedBy": [
        {
          "uid": "44362f55-106"
        },
        {
          "uid": "44362f55-170"
        },
        {
          "uid": "44362f55-68"
        },
        {
          "uid": "44362f55-70"
        },
        {
          "uid": "44362f55-72"
        },
        {
          "uid": "44362f55-74"
        },
        {
          "uid": "44362f55-76"
        },
        {
          "uid": "44362f55-78"
        },
        {
          "uid": "44362f55-80"
        },
        {
          "uid": "44362f55-82"
        },
        {
          "uid": "44362f55-84"
        }
      ]
    },
    "44362f55-68": {
      "id": "C:/Users/Akilesh/Documents/Flyen/src/shared/seo/templates/homeSEO.js",
      "moduleParts": {
        "entry-server.js": "44362f55-69"
      },
      "imported": [
        {
          "uid": "44362f55-62"
        },
        {
          "uid": "44362f55-66"
        }
      ],
      "importedBy": [
        {
          "uid": "44362f55-86"
        }
      ]
    },
    "44362f55-70": {
      "id": "C:/Users/Akilesh/Documents/Flyen/src/shared/seo/templates/projectListingSEO.js",
      "moduleParts": {
        "entry-server.js": "44362f55-71"
      },
      "imported": [
        {
          "uid": "44362f55-62"
        },
        {
          "uid": "44362f55-66"
        }
      ],
      "importedBy": [
        {
          "uid": "44362f55-86"
        }
      ]
    },
    "44362f55-72": {
      "id": "C:/Users/Akilesh/Documents/Flyen/src/shared/seo/templates/projectSEO.js",
      "moduleParts": {
        "entry-server.js": "44362f55-73"
      },
      "imported": [
        {
          "uid": "44362f55-62"
        },
        {
          "uid": "44362f55-66"
        }
      ],
      "importedBy": [
        {
          "uid": "44362f55-86"
        }
      ]
    },
    "44362f55-74": {
      "id": "C:/Users/Akilesh/Documents/Flyen/src/shared/seo/templates/contactSEO.js",
      "moduleParts": {
        "entry-server.js": "44362f55-75"
      },
      "imported": [
        {
          "uid": "44362f55-62"
        },
        {
          "uid": "44362f55-66"
        }
      ],
      "importedBy": [
        {
          "uid": "44362f55-86"
        }
      ]
    },
    "44362f55-76": {
      "id": "C:/Users/Akilesh/Documents/Flyen/src/shared/seo/templates/printingSEO.js",
      "moduleParts": {
        "entry-server.js": "44362f55-77"
      },
      "imported": [
        {
          "uid": "44362f55-62"
        },
        {
          "uid": "44362f55-66"
        }
      ],
      "importedBy": [
        {
          "uid": "44362f55-86"
        }
      ]
    },
    "44362f55-78": {
      "id": "C:/Users/Akilesh/Documents/Flyen/src/shared/seo/templates/aboutSEO.js",
      "moduleParts": {
        "entry-server.js": "44362f55-79"
      },
      "imported": [
        {
          "uid": "44362f55-62"
        },
        {
          "uid": "44362f55-66"
        }
      ],
      "importedBy": [
        {
          "uid": "44362f55-86"
        }
      ]
    },
    "44362f55-80": {
      "id": "C:/Users/Akilesh/Documents/Flyen/src/shared/seo/templates/departmentsSEO.js",
      "moduleParts": {
        "entry-server.js": "44362f55-81"
      },
      "imported": [
        {
          "uid": "44362f55-62"
        },
        {
          "uid": "44362f55-66"
        }
      ],
      "importedBy": [
        {
          "uid": "44362f55-86"
        }
      ]
    },
    "44362f55-82": {
      "id": "C:/Users/Akilesh/Documents/Flyen/src/shared/seo/templates/privacySEO.js",
      "moduleParts": {
        "entry-server.js": "44362f55-83"
      },
      "imported": [
        {
          "uid": "44362f55-62"
        },
        {
          "uid": "44362f55-66"
        }
      ],
      "importedBy": [
        {
          "uid": "44362f55-86"
        }
      ]
    },
    "44362f55-84": {
      "id": "C:/Users/Akilesh/Documents/Flyen/src/shared/seo/templates/termsSEO.js",
      "moduleParts": {
        "entry-server.js": "44362f55-85"
      },
      "imported": [
        {
          "uid": "44362f55-62"
        },
        {
          "uid": "44362f55-66"
        }
      ],
      "importedBy": [
        {
          "uid": "44362f55-86"
        }
      ]
    },
    "44362f55-86": {
      "id": "C:/Users/Akilesh/Documents/Flyen/src/shared/seo/generateSEO.js",
      "moduleParts": {
        "entry-server.js": "44362f55-87"
      },
      "imported": [
        {
          "uid": "44362f55-64"
        },
        {
          "uid": "44362f55-68"
        },
        {
          "uid": "44362f55-70"
        },
        {
          "uid": "44362f55-72"
        },
        {
          "uid": "44362f55-74"
        },
        {
          "uid": "44362f55-76"
        },
        {
          "uid": "44362f55-78"
        },
        {
          "uid": "44362f55-80"
        },
        {
          "uid": "44362f55-82"
        },
        {
          "uid": "44362f55-84"
        }
      ],
      "importedBy": [
        {
          "uid": "44362f55-106"
        },
        {
          "uid": "44362f55-172"
        }
      ]
    },
    "44362f55-88": {
      "id": "C:/Users/Akilesh/Documents/Flyen/src/shared/seo/routeMetadata.js",
      "moduleParts": {
        "entry-server.js": "44362f55-89"
      },
      "imported": [
        {
          "uid": "44362f55-0"
        },
        {
          "uid": "44362f55-64"
        }
      ],
      "importedBy": [
        {
          "uid": "44362f55-106"
        },
        {
          "uid": "44362f55-172"
        }
      ]
    },
    "44362f55-90": {
      "id": "C:/Users/Akilesh/Documents/Flyen/src/shared/seo/builders/metaBuilder.js",
      "moduleParts": {
        "entry-server.js": "44362f55-91"
      },
      "imported": [],
      "importedBy": [
        {
          "uid": "44362f55-106"
        },
        {
          "uid": "44362f55-170"
        }
      ]
    },
    "44362f55-92": {
      "id": "C:/Users/Akilesh/Documents/Flyen/src/shared/seo/builders/ogGenerator.js",
      "moduleParts": {
        "entry-server.js": "44362f55-93"
      },
      "imported": [],
      "importedBy": [
        {
          "uid": "44362f55-106"
        },
        {
          "uid": "44362f55-170"
        }
      ]
    },
    "44362f55-94": {
      "id": "C:/Users/Akilesh/Documents/Flyen/src/shared/seo/builders/twitterCard.js",
      "moduleParts": {
        "entry-server.js": "44362f55-95"
      },
      "imported": [],
      "importedBy": [
        {
          "uid": "44362f55-106"
        },
        {
          "uid": "44362f55-170"
        }
      ]
    },
    "44362f55-96": {
      "id": "C:/Users/Akilesh/Documents/Flyen/src/shared/seo/schemas/OrganizationSchema.js",
      "moduleParts": {
        "entry-server.js": "44362f55-97"
      },
      "imported": [],
      "importedBy": [
        {
          "uid": "44362f55-106"
        },
        {
          "uid": "44362f55-170"
        }
      ]
    },
    "44362f55-98": {
      "id": "C:/Users/Akilesh/Documents/Flyen/src/shared/seo/schemas/WebsiteSchema.js",
      "moduleParts": {
        "entry-server.js": "44362f55-99"
      },
      "imported": [],
      "importedBy": [
        {
          "uid": "44362f55-106"
        },
        {
          "uid": "44362f55-170"
        }
      ]
    },
    "44362f55-100": {
      "id": "C:/Users/Akilesh/Documents/Flyen/src/shared/seo/schemas/ProductSchema.js",
      "moduleParts": {
        "entry-server.js": "44362f55-101"
      },
      "imported": [],
      "importedBy": [
        {
          "uid": "44362f55-106"
        },
        {
          "uid": "44362f55-170"
        }
      ]
    },
    "44362f55-102": {
      "id": "C:/Users/Akilesh/Documents/Flyen/src/shared/seo/schemas/BreadcrumbSchema.js",
      "moduleParts": {
        "entry-server.js": "44362f55-103"
      },
      "imported": [],
      "importedBy": [
        {
          "uid": "44362f55-106"
        },
        {
          "uid": "44362f55-170"
        }
      ]
    },
    "44362f55-104": {
      "id": "C:/Users/Akilesh/Documents/Flyen/src/shared/seo/schemas/LocalBusinessSchema.js",
      "moduleParts": {
        "entry-server.js": "44362f55-105"
      },
      "imported": [],
      "importedBy": [
        {
          "uid": "44362f55-106"
        },
        {
          "uid": "44362f55-170"
        }
      ]
    },
    "44362f55-106": {
      "id": "C:/Users/Akilesh/Documents/Flyen/src/shared/seo/index.js",
      "moduleParts": {
        "entry-server.js": "44362f55-107"
      },
      "imported": [
        {
          "uid": "44362f55-60"
        },
        {
          "uid": "44362f55-62"
        },
        {
          "uid": "44362f55-64"
        },
        {
          "uid": "44362f55-86"
        },
        {
          "uid": "44362f55-88"
        },
        {
          "uid": "44362f55-66"
        },
        {
          "uid": "44362f55-90"
        },
        {
          "uid": "44362f55-92"
        },
        {
          "uid": "44362f55-94"
        },
        {
          "uid": "44362f55-184"
        },
        {
          "uid": "44362f55-185"
        },
        {
          "uid": "44362f55-96"
        },
        {
          "uid": "44362f55-98"
        },
        {
          "uid": "44362f55-100"
        },
        {
          "uid": "44362f55-102"
        },
        {
          "uid": "44362f55-104"
        },
        {
          "uid": "44362f55-186"
        }
      ],
      "importedBy": [
        {
          "uid": "44362f55-108"
        },
        {
          "uid": "44362f55-132"
        },
        {
          "uid": "44362f55-138"
        },
        {
          "uid": "44362f55-144"
        },
        {
          "uid": "44362f55-150"
        }
      ]
    },
    "44362f55-108": {
      "id": "C:/Users/Akilesh/Documents/Flyen/src/modules/public/pages/Home.jsx",
      "moduleParts": {
        "entry-server.js": "44362f55-109"
      },
      "imported": [
        {
          "uid": "44362f55-178"
        },
        {
          "uid": "44362f55-181"
        },
        {
          "uid": "44362f55-183"
        },
        {
          "uid": "44362f55-16"
        },
        {
          "uid": "44362f55-34"
        },
        {
          "uid": "44362f55-42"
        },
        {
          "uid": "44362f55-44"
        },
        {
          "uid": "44362f55-46"
        },
        {
          "uid": "44362f55-48"
        },
        {
          "uid": "44362f55-50"
        },
        {
          "uid": "44362f55-58"
        },
        {
          "uid": "44362f55-0"
        },
        {
          "uid": "44362f55-56"
        },
        {
          "uid": "44362f55-106"
        },
        {
          "uid": "44362f55-182"
        }
      ],
      "importedBy": [
        {
          "uid": "44362f55-176"
        }
      ]
    },
    "44362f55-110": {
      "id": "C:/Users/Akilesh/Documents/Flyen/src/modules/projects/hooks/useFilters.js",
      "moduleParts": {
        "entry-server.js": "44362f55-111"
      },
      "imported": [
        {
          "uid": "44362f55-178"
        }
      ],
      "importedBy": [
        {
          "uid": "44362f55-132"
        }
      ]
    },
    "44362f55-112": {
      "id": "C:/Users/Akilesh/Documents/Flyen/src/modules/projects/hooks/useSearch.js",
      "moduleParts": {
        "entry-server.js": "44362f55-113"
      },
      "imported": [
        {
          "uid": "44362f55-178"
        }
      ],
      "importedBy": [
        {
          "uid": "44362f55-132"
        }
      ]
    },
    "44362f55-114": {
      "id": "C:/Users/Akilesh/Documents/Flyen/src/modules/projects/hooks/useProjectFilters.js",
      "moduleParts": {
        "entry-server.js": "44362f55-115"
      },
      "imported": [
        {
          "uid": "44362f55-178"
        }
      ],
      "importedBy": [
        {
          "uid": "44362f55-132"
        }
      ]
    },
    "44362f55-116": {
      "id": "C:/Users/Akilesh/Documents/Flyen/src/shared/components/ui/AdminToolbar.jsx",
      "moduleParts": {
        "entry-server.js": "44362f55-117"
      },
      "imported": [
        {
          "uid": "44362f55-178"
        },
        {
          "uid": "44362f55-187"
        },
        {
          "uid": "44362f55-50"
        },
        {
          "uid": "44362f55-46"
        },
        {
          "uid": "44362f55-182"
        }
      ],
      "importedBy": [
        {
          "uid": "44362f55-132"
        }
      ]
    },
    "44362f55-118": {
      "id": "C:/Users/Akilesh/Documents/Flyen/src/modules/projects/constants/categories.js",
      "moduleParts": {
        "entry-server.js": "44362f55-119"
      },
      "imported": [],
      "importedBy": [
        {
          "uid": "44362f55-132"
        },
        {
          "uid": "44362f55-130"
        }
      ]
    },
    "44362f55-120": {
      "id": "C:/Users/Akilesh/Documents/Flyen/src/modules/projects/constants/difficulties.js",
      "moduleParts": {
        "entry-server.js": "44362f55-121"
      },
      "imported": [],
      "importedBy": [
        {
          "uid": "44362f55-132"
        }
      ]
    },
    "44362f55-122": {
      "id": "C:/Users/Akilesh/Documents/Flyen/src/modules/projects/constants/projectFeatures.js",
      "moduleParts": {
        "entry-server.js": "44362f55-123"
      },
      "imported": [],
      "importedBy": [
        {
          "uid": "44362f55-132"
        }
      ]
    },
    "44362f55-124": {
      "id": "C:/Users/Akilesh/Documents/Flyen/src/modules/projects/constants/projectBadges.js",
      "moduleParts": {
        "entry-server.js": "44362f55-125"
      },
      "imported": [],
      "importedBy": [
        {
          "uid": "44362f55-126"
        }
      ]
    },
    "44362f55-126": {
      "id": "C:/Users/Akilesh/Documents/Flyen/src/shared/components/ui/Badge.jsx",
      "moduleParts": {
        "entry-server.js": "44362f55-127"
      },
      "imported": [
        {
          "uid": "44362f55-178"
        },
        {
          "uid": "44362f55-124"
        },
        {
          "uid": "44362f55-182"
        }
      ],
      "importedBy": [
        {
          "uid": "44362f55-138"
        },
        {
          "uid": "44362f55-130"
        }
      ]
    },
    "44362f55-128": {
      "id": "C:/Users/Akilesh/Documents/Flyen/src/shared/components/ui/Card.jsx",
      "moduleParts": {
        "entry-server.js": "44362f55-129"
      },
      "imported": [
        {
          "uid": "44362f55-178"
        },
        {
          "uid": "44362f55-182"
        }
      ],
      "importedBy": [
        {
          "uid": "44362f55-130"
        }
      ]
    },
    "44362f55-130": {
      "id": "C:/Users/Akilesh/Documents/Flyen/src/modules/projects/components/ProjectGrid.jsx",
      "moduleParts": {
        "entry-server.js": "44362f55-131"
      },
      "imported": [
        {
          "uid": "44362f55-178"
        },
        {
          "uid": "44362f55-181"
        },
        {
          "uid": "44362f55-126"
        },
        {
          "uid": "44362f55-128"
        },
        {
          "uid": "44362f55-46"
        },
        {
          "uid": "44362f55-0"
        },
        {
          "uid": "44362f55-118"
        },
        {
          "uid": "44362f55-182"
        }
      ],
      "importedBy": [
        {
          "uid": "44362f55-132"
        },
        {
          "uid": "44362f55-134"
        }
      ]
    },
    "44362f55-132": {
      "id": "C:/Users/Akilesh/Documents/Flyen/src/modules/projects/pages/ProjectListing.jsx",
      "moduleParts": {
        "entry-server.js": "44362f55-133"
      },
      "imported": [
        {
          "uid": "44362f55-178"
        },
        {
          "uid": "44362f55-181"
        },
        {
          "uid": "44362f55-183"
        },
        {
          "uid": "44362f55-16"
        },
        {
          "uid": "44362f55-110"
        },
        {
          "uid": "44362f55-112"
        },
        {
          "uid": "44362f55-114"
        },
        {
          "uid": "44362f55-116"
        },
        {
          "uid": "44362f55-118"
        },
        {
          "uid": "44362f55-10"
        },
        {
          "uid": "44362f55-120"
        },
        {
          "uid": "44362f55-122"
        },
        {
          "uid": "44362f55-130"
        },
        {
          "uid": "44362f55-46"
        },
        {
          "uid": "44362f55-48"
        },
        {
          "uid": "44362f55-50"
        },
        {
          "uid": "44362f55-0"
        },
        {
          "uid": "44362f55-34"
        },
        {
          "uid": "44362f55-42"
        },
        {
          "uid": "44362f55-44"
        },
        {
          "uid": "44362f55-106"
        },
        {
          "uid": "44362f55-30"
        },
        {
          "uid": "44362f55-182"
        }
      ],
      "importedBy": [
        {
          "uid": "44362f55-176"
        }
      ]
    },
    "44362f55-134": {
      "id": "C:/Users/Akilesh/Documents/Flyen/src/modules/projects/components/RelatedProjects.jsx",
      "moduleParts": {
        "entry-server.js": "44362f55-135"
      },
      "imported": [
        {
          "uid": "44362f55-178"
        },
        {
          "uid": "44362f55-130"
        },
        {
          "uid": "44362f55-182"
        }
      ],
      "importedBy": [
        {
          "uid": "44362f55-138"
        }
      ]
    },
    "44362f55-136": {
      "id": "C:/Users/Akilesh/Documents/Flyen/src/modules/auth/components/ProgressiveAuthModal.jsx",
      "moduleParts": {
        "entry-server.js": "44362f55-137"
      },
      "imported": [
        {
          "uid": "44362f55-178"
        },
        {
          "uid": "44362f55-181"
        },
        {
          "uid": "44362f55-48"
        },
        {
          "uid": "44362f55-46"
        },
        {
          "uid": "44362f55-0"
        },
        {
          "uid": "44362f55-182"
        }
      ],
      "importedBy": [
        {
          "uid": "44362f55-138"
        }
      ]
    },
    "44362f55-138": {
      "id": "C:/Users/Akilesh/Documents/Flyen/src/modules/projects/pages/ProjectDetails.jsx",
      "moduleParts": {
        "entry-server.js": "44362f55-139"
      },
      "imported": [
        {
          "uid": "44362f55-178"
        },
        {
          "uid": "44362f55-181"
        },
        {
          "uid": "44362f55-183"
        },
        {
          "uid": "44362f55-16"
        },
        {
          "uid": "44362f55-134"
        },
        {
          "uid": "44362f55-126"
        },
        {
          "uid": "44362f55-46"
        },
        {
          "uid": "44362f55-48"
        },
        {
          "uid": "44362f55-50"
        },
        {
          "uid": "44362f55-0"
        },
        {
          "uid": "44362f55-34"
        },
        {
          "uid": "44362f55-56"
        },
        {
          "uid": "44362f55-44"
        },
        {
          "uid": "44362f55-42"
        },
        {
          "uid": "44362f55-136"
        },
        {
          "uid": "44362f55-106"
        },
        {
          "uid": "44362f55-30"
        },
        {
          "uid": "44362f55-182"
        }
      ],
      "importedBy": [
        {
          "uid": "44362f55-176"
        }
      ]
    },
    "44362f55-140": {
      "id": "C:/Users/Akilesh/Documents/Flyen/src/shared/config/printingProducts.json",
      "moduleParts": {
        "entry-server.js": "44362f55-141"
      },
      "imported": [],
      "importedBy": [
        {
          "uid": "44362f55-142"
        }
      ]
    },
    "44362f55-142": {
      "id": "C:/Users/Akilesh/Documents/Flyen/src/modules/public/hooks/usePrintingProducts.js",
      "moduleParts": {
        "entry-server.js": "44362f55-143"
      },
      "imported": [
        {
          "uid": "44362f55-178"
        },
        {
          "uid": "44362f55-140"
        }
      ],
      "importedBy": [
        {
          "uid": "44362f55-144"
        }
      ]
    },
    "44362f55-144": {
      "id": "C:/Users/Akilesh/Documents/Flyen/src/modules/public/pages/PrintingCatalog.jsx",
      "moduleParts": {
        "entry-server.js": "44362f55-145"
      },
      "imported": [
        {
          "uid": "44362f55-178"
        },
        {
          "uid": "44362f55-181"
        },
        {
          "uid": "44362f55-183"
        },
        {
          "uid": "44362f55-46"
        },
        {
          "uid": "44362f55-48"
        },
        {
          "uid": "44362f55-50"
        },
        {
          "uid": "44362f55-0"
        },
        {
          "uid": "44362f55-142"
        },
        {
          "uid": "44362f55-44"
        },
        {
          "uid": "44362f55-106"
        },
        {
          "uid": "44362f55-42"
        },
        {
          "uid": "44362f55-182"
        }
      ],
      "importedBy": [
        {
          "uid": "44362f55-176"
        }
      ]
    },
    "44362f55-146": {
      "id": "C:/Users/Akilesh/Documents/Flyen/src/modules/contact/services/contactService.js",
      "moduleParts": {
        "entry-server.js": "44362f55-147"
      },
      "imported": [
        {
          "uid": "44362f55-2"
        },
        {
          "uid": "44362f55-4"
        }
      ],
      "importedBy": [
        {
          "uid": "44362f55-150"
        }
      ]
    },
    "44362f55-148": {
      "id": "C:/Users/Akilesh/Documents/Flyen/src/modules/contact/services/emailService.js",
      "moduleParts": {
        "entry-server.js": "44362f55-149"
      },
      "imported": [
        {
          "uid": "44362f55-189"
        },
        {
          "uid": "44362f55-18"
        }
      ],
      "importedBy": [
        {
          "uid": "44362f55-150"
        }
      ]
    },
    "44362f55-150": {
      "id": "C:/Users/Akilesh/Documents/Flyen/src/modules/public/pages/Contact.jsx",
      "moduleParts": {
        "entry-server.js": "44362f55-151"
      },
      "imported": [
        {
          "uid": "44362f55-178"
        },
        {
          "uid": "44362f55-181"
        },
        {
          "uid": "44362f55-183"
        },
        {
          "uid": "44362f55-46"
        },
        {
          "uid": "44362f55-48"
        },
        {
          "uid": "44362f55-50"
        },
        {
          "uid": "44362f55-0"
        },
        {
          "uid": "44362f55-56"
        },
        {
          "uid": "44362f55-106"
        },
        {
          "uid": "44362f55-146"
        },
        {
          "uid": "44362f55-148"
        },
        {
          "uid": "44362f55-182"
        }
      ],
      "importedBy": [
        {
          "uid": "44362f55-176"
        }
      ]
    },
    "44362f55-152": {
      "id": "C:/Users/Akilesh/Documents/Flyen/src/shared/components/layout/NotificationDropdown.jsx",
      "moduleParts": {
        "entry-server.js": "44362f55-153"
      },
      "imported": [
        {
          "uid": "44362f55-178"
        },
        {
          "uid": "44362f55-181"
        },
        {
          "uid": "44362f55-18"
        },
        {
          "uid": "44362f55-182"
        }
      ],
      "importedBy": [
        {
          "uid": "44362f55-154"
        }
      ]
    },
    "44362f55-154": {
      "id": "C:/Users/Akilesh/Documents/Flyen/src/shared/components/layout/Header.jsx",
      "moduleParts": {
        "entry-server.js": "44362f55-155"
      },
      "imported": [
        {
          "uid": "44362f55-178"
        },
        {
          "uid": "44362f55-181"
        },
        {
          "uid": "44362f55-0"
        },
        {
          "uid": "44362f55-46"
        },
        {
          "uid": "44362f55-56"
        },
        {
          "uid": "44362f55-42"
        },
        {
          "uid": "44362f55-48"
        },
        {
          "uid": "44362f55-2"
        },
        {
          "uid": "44362f55-18"
        },
        {
          "uid": "44362f55-152"
        },
        {
          "uid": "44362f55-182"
        }
      ],
      "importedBy": [
        {
          "uid": "44362f55-174"
        }
      ]
    },
    "44362f55-156": {
      "id": "C:/Users/Akilesh/Documents/Flyen/src/shared/components/layout/GlowBackground.jsx",
      "moduleParts": {
        "entry-server.js": "44362f55-157"
      },
      "imported": [
        {
          "uid": "44362f55-178"
        },
        {
          "uid": "44362f55-182"
        }
      ],
      "importedBy": [
        {
          "uid": "44362f55-174"
        }
      ]
    },
    "44362f55-158": {
      "id": "C:/Users/Akilesh/Documents/Flyen/src/shared/config/navigation.js",
      "moduleParts": {
        "entry-server.js": "44362f55-159"
      },
      "imported": [],
      "importedBy": [
        {
          "uid": "44362f55-160"
        },
        {
          "uid": "44362f55-162"
        }
      ]
    },
    "44362f55-160": {
      "id": "C:/Users/Akilesh/Documents/Flyen/src/shared/components/layout/BottomNavigation.jsx",
      "moduleParts": {
        "entry-server.js": "44362f55-161"
      },
      "imported": [
        {
          "uid": "44362f55-178"
        },
        {
          "uid": "44362f55-181"
        },
        {
          "uid": "44362f55-158"
        },
        {
          "uid": "44362f55-42"
        },
        {
          "uid": "44362f55-0"
        },
        {
          "uid": "44362f55-182"
        }
      ],
      "importedBy": [
        {
          "uid": "44362f55-174"
        }
      ]
    },
    "44362f55-162": {
      "id": "C:/Users/Akilesh/Documents/Flyen/src/shared/components/layout/MobileDrawer.jsx",
      "moduleParts": {
        "entry-server.js": "44362f55-163"
      },
      "imported": [
        {
          "uid": "44362f55-178"
        },
        {
          "uid": "44362f55-181"
        },
        {
          "uid": "44362f55-183"
        },
        {
          "uid": "44362f55-158"
        },
        {
          "uid": "44362f55-42"
        },
        {
          "uid": "44362f55-46"
        },
        {
          "uid": "44362f55-0"
        },
        {
          "uid": "44362f55-182"
        }
      ],
      "importedBy": [
        {
          "uid": "44362f55-174"
        }
      ]
    },
    "44362f55-164": {
      "id": "C:/Users/Akilesh/Documents/Flyen/src/shared/components/layout/PageSettingsButton.jsx",
      "moduleParts": {
        "entry-server.js": "44362f55-165"
      },
      "imported": [
        {
          "uid": "44362f55-178"
        },
        {
          "uid": "44362f55-42"
        },
        {
          "uid": "44362f55-182"
        }
      ],
      "importedBy": [
        {
          "uid": "44362f55-174"
        }
      ]
    },
    "44362f55-166": {
      "id": "C:/Users/Akilesh/Documents/Flyen/src/shared/services/pageSettingsService.js",
      "moduleParts": {
        "entry-server.js": "44362f55-167"
      },
      "imported": [
        {
          "uid": "44362f55-2"
        },
        {
          "uid": "44362f55-8"
        }
      ],
      "importedBy": [
        {
          "uid": "44362f55-168"
        },
        {
          "uid": "44362f55-172"
        }
      ]
    },
    "44362f55-168": {
      "id": "C:/Users/Akilesh/Documents/Flyen/src/shared/components/layout/PageSettingsDrawer.jsx",
      "moduleParts": {
        "entry-server.js": "44362f55-169"
      },
      "imported": [
        {
          "uid": "44362f55-178"
        },
        {
          "uid": "44362f55-181"
        },
        {
          "uid": "44362f55-166"
        },
        {
          "uid": "44362f55-44"
        },
        {
          "uid": "44362f55-182"
        }
      ],
      "importedBy": [
        {
          "uid": "44362f55-174"
        }
      ]
    },
    "44362f55-170": {
      "id": "C:/Users/Akilesh/Documents/Flyen/src/shared/seo/metadataManager.js",
      "moduleParts": {
        "entry-server.js": "44362f55-171"
      },
      "imported": [
        {
          "uid": "44362f55-62"
        },
        {
          "uid": "44362f55-90"
        },
        {
          "uid": "44362f55-66"
        },
        {
          "uid": "44362f55-92"
        },
        {
          "uid": "44362f55-94"
        },
        {
          "uid": "44362f55-96"
        },
        {
          "uid": "44362f55-98"
        },
        {
          "uid": "44362f55-100"
        },
        {
          "uid": "44362f55-102"
        },
        {
          "uid": "44362f55-104"
        },
        {
          "uid": "44362f55-64"
        }
      ],
      "importedBy": [
        {
          "uid": "44362f55-172"
        }
      ]
    },
    "44362f55-172": {
      "id": "C:/Users/Akilesh/Documents/Flyen/src/shared/seo/usePageMetadata.js",
      "moduleParts": {
        "entry-server.js": "44362f55-173"
      },
      "imported": [
        {
          "uid": "44362f55-178"
        },
        {
          "uid": "44362f55-181"
        },
        {
          "uid": "44362f55-166"
        },
        {
          "uid": "44362f55-170"
        },
        {
          "uid": "44362f55-0"
        },
        {
          "uid": "44362f55-88"
        },
        {
          "uid": "44362f55-64"
        },
        {
          "uid": "44362f55-86"
        },
        {
          "uid": "44362f55-2"
        }
      ],
      "importedBy": [
        {
          "uid": "44362f55-174"
        }
      ]
    },
    "44362f55-174": {
      "id": "C:/Users/Akilesh/Documents/Flyen/src/shared/components/layout/MainLayout.jsx",
      "moduleParts": {
        "entry-server.js": "44362f55-175"
      },
      "imported": [
        {
          "uid": "44362f55-178"
        },
        {
          "uid": "44362f55-181"
        },
        {
          "uid": "44362f55-154"
        },
        {
          "uid": "44362f55-156"
        },
        {
          "uid": "44362f55-160"
        },
        {
          "uid": "44362f55-162"
        },
        {
          "uid": "44362f55-164"
        },
        {
          "uid": "44362f55-168"
        },
        {
          "uid": "44362f55-172"
        },
        {
          "uid": "44362f55-182"
        }
      ],
      "importedBy": [
        {
          "uid": "44362f55-176"
        }
      ]
    },
    "44362f55-176": {
      "id": "C:/Users/Akilesh/Documents/Flyen/src/entry-server.jsx",
      "moduleParts": {
        "entry-server.js": "44362f55-177"
      },
      "imported": [
        {
          "uid": "44362f55-178"
        },
        {
          "uid": "44362f55-179"
        },
        {
          "uid": "44362f55-180"
        },
        {
          "uid": "44362f55-181"
        },
        {
          "uid": "44362f55-0"
        },
        {
          "uid": "44362f55-108"
        },
        {
          "uid": "44362f55-132"
        },
        {
          "uid": "44362f55-138"
        },
        {
          "uid": "44362f55-144"
        },
        {
          "uid": "44362f55-150"
        },
        {
          "uid": "44362f55-54"
        },
        {
          "uid": "44362f55-14"
        },
        {
          "uid": "44362f55-42"
        },
        {
          "uid": "44362f55-44"
        },
        {
          "uid": "44362f55-32"
        },
        {
          "uid": "44362f55-174"
        },
        {
          "uid": "44362f55-182"
        }
      ],
      "importedBy": [],
      "isEntry": true
    },
    "44362f55-178": {
      "id": "react",
      "moduleParts": {},
      "imported": [],
      "importedBy": [
        {
          "uid": "44362f55-176"
        },
        {
          "uid": "44362f55-108"
        },
        {
          "uid": "44362f55-132"
        },
        {
          "uid": "44362f55-138"
        },
        {
          "uid": "44362f55-144"
        },
        {
          "uid": "44362f55-150"
        },
        {
          "uid": "44362f55-54"
        },
        {
          "uid": "44362f55-14"
        },
        {
          "uid": "44362f55-42"
        },
        {
          "uid": "44362f55-44"
        },
        {
          "uid": "44362f55-32"
        },
        {
          "uid": "44362f55-174"
        },
        {
          "uid": "44362f55-16"
        },
        {
          "uid": "44362f55-34"
        },
        {
          "uid": "44362f55-46"
        },
        {
          "uid": "44362f55-48"
        },
        {
          "uid": "44362f55-50"
        },
        {
          "uid": "44362f55-58"
        },
        {
          "uid": "44362f55-56"
        },
        {
          "uid": "44362f55-110"
        },
        {
          "uid": "44362f55-112"
        },
        {
          "uid": "44362f55-114"
        },
        {
          "uid": "44362f55-116"
        },
        {
          "uid": "44362f55-130"
        },
        {
          "uid": "44362f55-134"
        },
        {
          "uid": "44362f55-126"
        },
        {
          "uid": "44362f55-136"
        },
        {
          "uid": "44362f55-142"
        },
        {
          "uid": "44362f55-154"
        },
        {
          "uid": "44362f55-156"
        },
        {
          "uid": "44362f55-160"
        },
        {
          "uid": "44362f55-162"
        },
        {
          "uid": "44362f55-164"
        },
        {
          "uid": "44362f55-168"
        },
        {
          "uid": "44362f55-172"
        },
        {
          "uid": "44362f55-60"
        },
        {
          "uid": "44362f55-128"
        },
        {
          "uid": "44362f55-24"
        },
        {
          "uid": "44362f55-28"
        },
        {
          "uid": "44362f55-152"
        }
      ]
    },
    "44362f55-179": {
      "id": "react-dom/server",
      "moduleParts": {},
      "imported": [],
      "importedBy": [
        {
          "uid": "44362f55-176"
        }
      ]
    },
    "44362f55-180": {
      "id": "react-router-dom/server.mjs",
      "moduleParts": {},
      "imported": [],
      "importedBy": [
        {
          "uid": "44362f55-176"
        }
      ]
    },
    "44362f55-181": {
      "id": "react-router-dom",
      "moduleParts": {},
      "imported": [],
      "importedBy": [
        {
          "uid": "44362f55-176"
        },
        {
          "uid": "44362f55-108"
        },
        {
          "uid": "44362f55-132"
        },
        {
          "uid": "44362f55-138"
        },
        {
          "uid": "44362f55-144"
        },
        {
          "uid": "44362f55-150"
        },
        {
          "uid": "44362f55-174"
        },
        {
          "uid": "44362f55-58"
        },
        {
          "uid": "44362f55-130"
        },
        {
          "uid": "44362f55-136"
        },
        {
          "uid": "44362f55-154"
        },
        {
          "uid": "44362f55-160"
        },
        {
          "uid": "44362f55-162"
        },
        {
          "uid": "44362f55-168"
        },
        {
          "uid": "44362f55-172"
        },
        {
          "uid": "44362f55-24"
        },
        {
          "uid": "44362f55-152"
        }
      ]
    },
    "44362f55-182": {
      "id": "react/jsx-runtime",
      "moduleParts": {},
      "imported": [],
      "importedBy": [
        {
          "uid": "44362f55-176"
        },
        {
          "uid": "44362f55-108"
        },
        {
          "uid": "44362f55-132"
        },
        {
          "uid": "44362f55-138"
        },
        {
          "uid": "44362f55-144"
        },
        {
          "uid": "44362f55-150"
        },
        {
          "uid": "44362f55-54"
        },
        {
          "uid": "44362f55-14"
        },
        {
          "uid": "44362f55-42"
        },
        {
          "uid": "44362f55-44"
        },
        {
          "uid": "44362f55-32"
        },
        {
          "uid": "44362f55-174"
        },
        {
          "uid": "44362f55-46"
        },
        {
          "uid": "44362f55-48"
        },
        {
          "uid": "44362f55-50"
        },
        {
          "uid": "44362f55-58"
        },
        {
          "uid": "44362f55-116"
        },
        {
          "uid": "44362f55-130"
        },
        {
          "uid": "44362f55-134"
        },
        {
          "uid": "44362f55-126"
        },
        {
          "uid": "44362f55-136"
        },
        {
          "uid": "44362f55-154"
        },
        {
          "uid": "44362f55-156"
        },
        {
          "uid": "44362f55-160"
        },
        {
          "uid": "44362f55-162"
        },
        {
          "uid": "44362f55-164"
        },
        {
          "uid": "44362f55-168"
        },
        {
          "uid": "44362f55-128"
        },
        {
          "uid": "44362f55-24"
        },
        {
          "uid": "44362f55-152"
        }
      ]
    },
    "44362f55-183": {
      "id": "framer-motion",
      "moduleParts": {},
      "imported": [],
      "importedBy": [
        {
          "uid": "44362f55-108"
        },
        {
          "uid": "44362f55-132"
        },
        {
          "uid": "44362f55-138"
        },
        {
          "uid": "44362f55-144"
        },
        {
          "uid": "44362f55-150"
        },
        {
          "uid": "44362f55-162"
        }
      ]
    },
    "44362f55-184": {
      "id": "C:/Users/Akilesh/Documents/Flyen/src/shared/seo/robotsGenerator.js",
      "moduleParts": {},
      "imported": [],
      "importedBy": [
        {
          "uid": "44362f55-106"
        }
      ]
    },
    "44362f55-185": {
      "id": "C:/Users/Akilesh/Documents/Flyen/src/shared/seo/sitemapGenerator.js",
      "moduleParts": {},
      "imported": [],
      "importedBy": [
        {
          "uid": "44362f55-106"
        }
      ]
    },
    "44362f55-186": {
      "id": "C:/Users/Akilesh/Documents/Flyen/src/shared/seo/schemas/FAQSchema.js",
      "moduleParts": {},
      "imported": [],
      "importedBy": [
        {
          "uid": "44362f55-106"
        }
      ]
    },
    "44362f55-187": {
      "id": "react-dom",
      "moduleParts": {},
      "imported": [],
      "importedBy": [
        {
          "uid": "44362f55-116"
        }
      ]
    },
    "44362f55-188": {
      "id": "C:/Users/Akilesh/Documents/Flyen/src/shared/analytics/analyticsConfig.js",
      "moduleParts": {},
      "imported": [],
      "importedBy": [
        {
          "uid": "44362f55-30"
        },
        {
          "uid": "44362f55-22"
        }
      ]
    },
    "44362f55-189": {
      "id": "@emailjs/browser",
      "moduleParts": {},
      "imported": [],
      "importedBy": [
        {
          "uid": "44362f55-148"
        }
      ]
    },
    "44362f55-190": {
      "id": "@supabase/supabase-js",
      "moduleParts": {},
      "imported": [],
      "importedBy": [
        {
          "uid": "44362f55-2"
        }
      ]
    }
  },
  "env": {
    "rollup": "4.23.0"
  },
  "options": {
    "gzip": false,
    "brotli": false,
    "sourcemap": false
  }
}